timestomp/__init__.py
timestomp-0.0.3.dist-info/LICENSE
timestomp-0.0.3.dist-info/METADATA
timestomp-0.0.3.dist-info/WHEEL
timestomp-0.0.3.dist-info/top_level.txt
timestomp-0.0.3.dist-info/RECORD
