Metadata-Version: 2.1
Name: timestomp
Version: 0.0.3
Summary: Stamp
Author: SmartMozart
License: UNKNOWN
Platform: UNKNOWN
Requires-Python: >=3.6
License-File: LICENSE
